Workbook

Sheet Introducción
A1: Objetivo del libro de Excel
A2: El objetivo de este libro es simular la acumulación de un fondo de inversión a lo largo del tiempo y analizar los posibles retiros, considerando diferentes parámetros como aportaciones, intereses, inflación y requerimientos de efectivo. Así, permite planificar financieramente el crecimiento
A3: y la sostenibilidad del fondo, anticipando cuándo podrían superarse los ingresos por los retiros y en qué momento se agotaría el fondo, para tomar decisiones.
A5: 1. Acumulación
A6: Descripción: Esta hoja simula el crecimiento del fondo a través de aportaciones anuales y el cálculo de intereses compuestos. Incluye una tabla donde se muestra, año a año, el saldo inicial, la aportación anual, los intereses ganados, el saldo final y la suma acumulada de aportaciones.
A7: Indicaciones de uso:
A8: * Puedes modificar los parámetros en azul, como el monto inicial del fondo, la aportación anual y la tasa de interés promedio ponderado.
A9: * Observa cómo varía el saldo final y los intereses ganados a lo largo de los años.
A10: * Útil para proyectar cuánto podrías acumular en el fondo bajo diferentes escenarios de aportación y rendimiento.
A12: 2. Retiros
A13: Descripción: Esta hoja está orientada a la simulación de ingresos y retiros del fondo, considerando inversiones tanto en el país (EL SAL) como en el extranjero, tasas de cambio, tasas de interés y requerimientos de efectivo (en euros y dólares). Incluye escenarios con y sin inflación,
A14: mostrando cómo varían los requerimientos y el monto disponible para invertir.
... A31: Utiliza los resultados para tomar decisiones informadas sobre tus aportaciones, inversiones y retiros futuros.

Sheet Acumulación
A1: Simulación Acumulación
A3: Parámetros editables | E3: Saldo | F3: Aportación | G3: Intereses | H3: Saldo | I3: Aportación
D4: Año | E4: incial | F4: anual | G4: ganados | H4: final | I4: acumulada
A5: Monto inicial del fondo | B5: 10000 | D5: 1 | E5: =+B5 -> 10000 | F5: =+B6 -> 5000 | G5: =+(E5+F5)*$B$7 -> 600 | H5: =+E5+F5+G5 -> 15600 | I5: =+F5 -> 5000
A6: Monto de inversión anual | B6: 5000 | D6: 2 | E6: =+H5 -> 15600 | F6: =+F5 -> 5000 | G6: =+(E6+F6)*$B$7 -> 824 | H6: =+E6+F6+G6 -> 21424 | I6: =+I5+F6 -> 10000
A7: Tasa promedio ponderado de inversiones | B7: 0.04 | D7: 3 | E7: =+H6 -> 21424 | F7: =+F6 -> 5000 | G7: =+(E7+F7)*$B$7 -> 1056.96 | H7: =+E7+F7+G7 -> 27480.96 | I7: =+I6+F7 -> 15000
D8: 4 | E8: =+H7 -> 27480.96 | F8: =+F7 -> 5000 | G8: =+(E8+F8)*$B$7 -> 1299.2384 | H8: =+E8+F8+G8 -> 33780.198 | I8: =+I7+F8 -> 20000
D9: 5 | E9: =+H8 -> 33780.198 | F9: =+F8 -> 5000 | G9: =+(E9+F9)*$B$7 -> 1551.2079 | H9: =+E9+F9+G9 -> 40331.406 | I9: =+I8+F9 -> 25000
D10: 6 | E10: =+H9 -> 40331.406 | F10: =+F9 -> 5000 | G10: =+(E10+F10)*$B$7 -> 1813.2563 | H10: =+E10+F10+G10 -> 47144.663 | I10: =+I9+F10 -> 30000
D11: 7 | E11: =+H10 -> 47144.663 | F11: =+F10 -> 5000 | G11: =+(E11+F11)*$B$7 -> 2085.7865 | H11: =+E11+F11+G11 -> 54230.449 | I11: =+I10+F11 -> 35000
D12: 8 | E12: =+H11 -> 54230.449 | F12: =+F11 -> 5000 | G12: =+(E12+F12)*$B$7 -> 2369.218 | H12: =+E12+F12+G12 -> 61599.667 | I12: =+I11+F12 -> 40000
D13: 9 | E13: =+H12 -> 61599.667 | F13: =+F12 -> 5000 | G13: =+(E13+F13)*$B$7 -> 2663.9867 | H13: =+E13+F13+G13 -> 69263.654 | I13: =+I12+F13 -> 45000
D14: 10 | E14: =+H13 -> 69263.654 | F14: =+F13 -> 5000 | G14: =+(E14+F14)*$B$7 -> 2970.5461 | H14: =+E14+F14+G14 -> 77234.2 | I14: =+I13+F14 -> 50000
D15: 11 | E15: =+H14 -> 77234.2 | F15: =+F14 -> 5000 | G15: =+(E15+F15)*$B$7 -> 3289.368 | H15: =+E15+F15+G15 -> 85523.568 | I15: =+I14+F15 -> 55000
D16: 12 | E16: =+H15 -> 85523.568 | F16: =+F15 -> 5000 | G16: =+(E16+F16)*$B$7 -> 3620.9427 | H16: =+E16+F16+G16 -> 94144.511 | I16: =+I15+F16 -> 60000
D17: 13 | E17: =+H16 -> 94144.511 | F17: =+F16 -> 5000 | G17: =+(E17+F17)*$B$7 -> 3965.7804 | H17: =+E17+F17+G17 -> 103110.29 | I17: =+I16+F17 -> 65000
D18: 14 | E18: =+H17 -> 103110.29 | F18: =+F17 -> 5000 | G18: =+(E18+F18)*$B$7 -> 4324.4116 | H18: =+E18+F18+G18 -> 112434.7 | I18: =+I17+F18 -> 70000
D19: 15 | E19: =+H18 -> 112434.7 | F19: =+F18 -> 5000 | G19: =+(E19+F19)*$B$7 -> 4697.3881 | H19: =+E19+F19+G19 -> 122132.09 | I19: =+I18+F19 -> 75000
... D44: 40 | E44: =+H43 -> 516291.24 | F44: =+F43 -> 5000 | G44: =+(E44+F44)*$B$7 -> 20851.65 | H44: =+E44+F44+G44 -> 542142.89 | I44: =+I43+F44 -> 200000
F45: =SUM(F5:F44) -> 200000 | G45: =SUM(G5:G44) -> 332142.89 | H45: =+G45+F45 -> 532142.89

Sheet Retiros
A1: Simulación de ingresos e inversiones de REFC 2026 | C1: Importante. Lo que está en AZUL se puede editar, lo que está en color Negro no.
A3: Parámetros editables
D4: Escenario sin inflación | I4: Ingreso anual teórico de fondos invertidos | M4: Ingreso teórico versus requerimiento de efectivo
A5: Monto total disponible para invertir (Fondo) | B5: 220000 | D5: Monto disponible para invertir en ELSAL | G5: =+B5-B10 -> 160000 | I5: Totalmente en ELSAL | K5: =+B5*B9 -> 17600 | M5: =+K5-$H$11 -> 6080
A6: Monto ya invertido en ELSAL | B6: 100000 | D6: Monto que falta por invertir en ELSAL | G6: =+G5-B6 -> 60000 | I6: Totalmente en extranjero | K6: =+B5*B11 -> 8800 | M6: =+K6-$H$11 -> -2720
A7: Requerimiento mensual de efectivo en euros | B7: 800 | D7: Ingresos anuales de inversiones ELSAL | G7: =+B6*B9 -> 8000 | I7: En ELSAL y extranjero | K7: =+G5*B9+B10*B11 -> 15200 | M7: =+K7-$H$11 -> 3680
A8: Tasa de cambio euro → dólar | B8: 1.2 | I8: Tasa de interés de inversiones (promedio ponderado) | M8: =+K7/B5 -> 0.069090909
A9: Tasa promedio ponderado inversiones actuales ELSAL | B9: 0.08 | D9: Requerimiento
A10: Fondo de seguridad en extranjero | B10: 60000 | D10: Anual de efectivo en euros | H10: =+B7*12 -> 9600 | N10: Riesgos
A11: Tasa promedio ponderado de inversiones en el extranjero | B11: 0.04 | D11: Requerimiento anual de efectivo en dólares | H11: =+H10*B8 -> 11520 | N11: Tasa de interés
A12: Tasa de inflación anual esperada en España (país de residencia) | B12: 0.03 | D12: Tasa de interés de inversiones (promedio ponderado) | H12: =+H11/B5 -> 0.052363636 | N12: Riesgo país
N13: Riesgo tasa de cambio
N14: Riesgo inflación
D15: Escenario con inflación
D16: Requerimientos anuales - dólares con inflación | I16: Requerimientos anuales con incremento del FONDO - dólares con inflación
D17: Año | E17: Efectivo | F17: Tasa interés | I17: Año | J17: Monto a invertir | K17: Incremento | L17: Tasa interés
D18: 1 | E18: =+H11*(1+$B$12) -> 11865.6 | F18: =+E18/$B$5 -> 0.053934545 | I18: 1 | J18: =+B5*(1+B12) -> 226600 | K18: =+J18-B5 -> 6600 | L18: =+E18/J18 -> 0.052363636
D19: 2 | E19: =+E18*(1+$B$12) -> 12221.568 | F19: =+E19/$B$5 -> 0.055552582 | I19: 2 | J19: =+J18*(1+$B$12) -> 233398 | K19: =+J19-J18 -> 6798 | L19: =+E19/J19 -> 0.052363636
D20: 3 | E20: =+E19*(1+$B$12) -> 12588.215 | F20: =+E20/$B$5 -> 0.057219159 | I20: 3 | J20: =+J19*(1+$B$12) -> 240399.94 | K20: =+J20-J19 -> 7001.94 | L20: =+E20/J20 -> 0.052363636
D21: 4 | E21: =+E20*(1+$B$12) -> 12965.861 | F21: =+E21/$B$5 -> 0.058935734 | I21: 4 | J21: =+J20*(1+$B$12) -> 247611.94 | K21: =+J21-J20 -> 7211.9982 | L21: =+E21/J21 -> 0.052363636
D22: 5 | E22: =+E21*(1+$B$12) -> 13354.837 | F22: =+E22/$B$5 -> 0.060703806 | I22: 5 | J22: =+J21*(1+$B$12) -> 255040.3 | K22: =+J22-J21 -> 7428.3581 | L22: =+E22/J22 -> 0.052363636
D23: 6 | E23: =+E22*(1+$B$12) -> 13755.482 | F23: =+E23/$B$5 -> 0.06252492 | I23: 6 | J23: =+J22*(1+$B$12) -> 262691.51 | K23: =+J23-J22 -> 7651.2089 | L23: =+E23/J23 -> 0.052363636
D24: 7 | E24: =+E23*(1+$B$12) -> 14168.147 | F24: =+E24/$B$5 -> 0.064400668 | I24: 7 | J24: =+J23*(1+$B$12) -> 270572.25 | K24: =+J24-J23 -> 7880.7452 | L24: =+E24/J24 -> 0.052363636
D25: 8 | E25: =+E24*(1+$B$12) -> 14593.191 | F25: =+E25/$B$5 -> 0.066332688 | I25: 8 | J25: =+J24*(1+$B$12) -> 278689.42 | K25: =+J25-J24 -> 8117.1675 | L25: =+E25/J25 -> 0.052363636
D26: 9 | E26: =+E25*(1+$B$12) -> 15030.987 | F26: =+E26/$B$5 -> 0.068322669 | I26: 9 | J26: =+J25*(1+$B$12) -> 287050.1 | K26: =+J26-J25 -> 8360.6825 | L26: =+E26/J26 -> 0.052363636
D27: 10 | E27: =+E26*(1+$B$12) -> 15481.917 | F27: =+E27/$B$5 -> 0.070372349 | I27: 10 | J27: =+J26*(1+$B$12) -> 295661.6 | K27: =+J27-J26 -> 8611.503 | L27: =+E27/J27 -> 0.052363636
D28: 11 | E28: =+E27*(1+$B$12) -> 15946.374 | F28: =+E28/$B$5 -> 0.072483519 | I28: 11 | J28: =+J27*(1+$B$12) -> 304531.45 | K28: =+J28-J27 -> 8869.8481 | L28: =+E28/J28 -> 0.052363636
D29: 12 | E29: =+E28*(1+$B$12) -> 16424.765 | F29: =+E29/$B$5 -> 0.074658025 | I29: 12 | J29: =+J28*(1+$B$12) -> 313667.4 | K29: =+J29-J28 -> 9135.9435 | L29: =+E29/J29 -> 0.052363636
D30: 13 | E30: =+E29*(1+$B$12) -> 16917.508 | F30: =+E30/$B$5 -> 0.076897765 | I30: 13 | J30: =+J29*(1+$B$12) -> 323077.42 | K30: =+J30-J29 -> 9410.0219 | L30: =+E30/J30 -> 0.052363636
... D52: 35 | E52: =+E51*(1+$B$12) -> 32415.695 | F52: =+E52/$B$5 -> 0.14734407 | I52: 35 | J52: =+J51*(1+$B$12) -> 619049.74 | K52: =+J52-J51 -> 18030.575 | L52: =+E52/J52 -> 0.052363636

Sheet Saldo del fondo
A1: Saldo del monto total disponible para invertir (Fondo)
B3: Saldo | C3: Intereses | E3: Saldo | G3: Poder | H3: ingresos - | I3: Cobertura
A4: Año | B4: inicial | C4: ganados | D4: Retiros | E4: final | G4: adquisitivo | H4: retiros | I4: en años
A5: 1 | B5: =+Retiros!B5 -> 220000 | C5: =+B5*Retiros!$M$8 -> 15200 | D5: =+Retiros!E18 -> 11865.6 | E5: =+B5+C5-D5 -> 223334.4 | G5: =+E5/(1+Retiros!$B$12) -> 216829.51 | H5: =+C5-D5 -> 3334.4 | I5: =+E5/D5 -> 18.822006 | K5: Supuestos vienen de la pestaña Datos (NO MODIFICAR AQUÍ)
A6: 2 | B6: =+E5 -> 223334.4 | C6: =+B6*Retiros!$M$8 -> 15430.377 | D6: =+D5*(1+Retiros!$B$12) -> 12221.568 | E6: =+B6+C6-D6 -> 226543.21 | G6: =+E6/(1+Retiros!$B$12) -> 219944.86 | H6: =+C6-D6 -> 3208.8087 | I6: =+E6/D6 -> 18.536346 | K6: Saldo inicial | N6: =+Retiros!B5 -> 220000 | P6: Datos!B4
A7: 3 | B7: =+E6 -> 226543.21 | C7: =+B7*Retiros!$M$8 -> 15652.076 | D7: =+D6*(1+Retiros!$B$12) -> 12588.215 | E7: =+B7+C7-D7 -> 229607.07 | G7: =+E7/(1+Retiros!$B$12) -> 222919.49 | H7: =+C7-D7 -> 3063.8612 | I7: =+E7/D7 -> 18.239843 | K7: Tasa de interés (promedio ponderado) | N7: =+Retiros!M8 -> 0.069090909 | P7: Datos!M7
A8: 4 | B8: =+E7 -> 229607.07 | C8: =+B8*Retiros!$M$8 -> 15863.761 | D8: =+D7*(1+Retiros!$B$12) -> 12965.861 | E8: =+B8+C8-D8 -> 232504.97 | G8: =+E8/(1+Retiros!$B$12) -> 225732.98 | H8: =+C8-D8 -> 2897.8997 | I8: =+E8/D8 -> 17.932088 | K8: Retiro (año 1) | N8: =+Retiros!E18 -> 11865.6 | P8: Datos!E17
A9: 5 | B9: =+E8 -> 232504.97 | C9: =+B9*Retiros!$M$8 -> 16063.98 | D9: =+D8*(1+Retiros!$B$12) -> 13354.837 | E9: =+B9+C9-D9 -> 235214.11 | G9: =+E9/(1+Retiros!$B$12) -> 228363.22 | H9: =+C9-D9 -> 2709.1424 | I9: =+E9/D9 -> 17.612653 | K9: Tasa de inflación (aplica a retiros) | N9: =+Retiros!B12 -> 0.03 | P9: Datos!B11
A10: 6 | B10: =+E9 -> 235214.11 | C10: =+B10*Retiros!$M$8 -> 16251.157 | D10: =+D9*(1+Retiros!$B$12) -> 13755.482 | E10: =+B10+C10-D10 -> 237709.79 | G10: =+E10/(1+Retiros!$B$12) -> 230786.2 | H10: =+C10-D10 -> 2495.6744 | I10: =+E10/D10 -> 17.281094
A11: 7 | B11: =+E10 -> 237709.79 | C11: =+B11*Retiros!$M$8 -> 16423.585 | D11: =+D10*(1+Retiros!$B$12) -> 14168.147 | E11: =+B11+C11-D11 -> 239965.22 | G11: =+E11/(1+Retiros!$B$12) -> 232975.95 | H11: =+C11-D11 -> 2255.4383 | I11: =+E11/D11 -> 16.936952 | K11: Concepto
A12: 8 | B12: =+E11 -> 239965.22 | C12: =+B12*Retiros!$M$8 -> 16579.416 | D12: =+D11*(1+Retiros!$B$12) -> 14593.191 | E12: =+B12+C12-D12 -> 241951.45 | G12: =+E12/(1+Retiros!$B$12) -> 234904.32 | H12: =+C12-D12 -> 1986.2242 | I12: =+E12/D12 -> 16.579749 | K12: Saldo inicial: Saldo al iniciar el año
A13: 9 | B13: =+E12 -> 241951.45 | C13: =+B13*Retiros!$M$8 -> 16716.646 | D13: =+D12*(1+Retiros!$B$12) -> 15030.987 | E13: =+B13+C13-D13 -> 243637.11 | G13: =+E13/(1+Retiros!$B$12) -> 236540.88 | H13: =+C13-D13 -> 1685.6585 | I13: =+E13/D13 -> 16.208989 | K13: Intereses ganados: saldo inicial x tasa de interés
A14: 10 | B14: =+E13 -> 243637.11 | C14: =+B14*Retiros!$M$8 -> 16833.109 | D14: =+D13*(1+Retiros!$B$12) -> 15481.917 | E14: =+B14+C14-D14 -> 244988.3 | G14: =+E14/(1+Retiros!$B$12) -> 237852.72 | H14: =+C14-D14 -> 1351.1925 | I14: =+E14/D14 -> 15.824158 | K14: Retiros: Efectivo requerido en el año
A15: 11 | B15: =+E14 -> 244988.3 | C15: =+B15*Retiros!$M$8 -> 16926.464 | D15: =+D14*(1+Retiros!$B$12) -> 15946.374 | E15: =+B15+C15-D15 -> 245968.39 | G15: =+E15/(1+Retiros!$B$12) -> 238804.26 | H15: =+C15-D15 -> 980.09017 | I15: =+E15/D15 -> 15.424722 | K15: Saldo final: Saldo inicial + intereses ganados - retiros
A16: 12 | B16: =+E15 -> 245968.39 | C16: =+B16*Retiros!$M$8 -> 16994.18 | D16: =+D15*(1+Retiros!$B$12) -> 16424.765 | E16: =+B16+C16-D16 -> 246537.8 | G16: =+E16/(1+Retiros!$B$12) -> 239357.09 | H16: =+C16-D16 -> 569.41426 | I16: =+E16/D16 -> 15.010126 | K16: Poder adquisitivo: Saldo ajustado por la inflación
A17: 13 | B17: =+E16 -> 246537.8 | C17: =+B17*Retiros!$M$8 -> 17033.521 | D17: =+D16*(1+Retiros!$B$12) -> 16917.508 | E17: =+B17+C17-D17 -> 246653.82 | G17: =+E17/(1+Retiros!$B$12) -> 239469.73 | H17: =+C17-D17 -> 116.01265 | I17: =+E17/D17 -> 14.579796 | K17: Ingresos - retiros: Diferencia anual (si es negativa se consume el capital)
A18: 14 | B18: =+E17 -> 246653.82 | C18: =+B18*Retiros!$M$8 -> 17041.536 | D18: =+D17*(1+Retiros!$B$12) -> 17425.034 | E18: =+B18+C18-D18 -> 246270.32 | G18: =+E18/(1+Retiros!$B$12) -> 239097.4 | H18: =+C18-D18 -> -383.49718 | I18: =+E18/D18 -> 14.133133
A19: 15 | B19: =+E18 -> 246270.32 | C19: =+B19*Retiros!$M$8 -> 17015.04 | D19: =+D18*(1+Retiros!$B$12) -> 17947.785 | E19: =+B19+C19-D19 -> 245337.58 | G19: =+E19/(1+Retiros!$B$12) -> 238191.82 | H19: =+C19-D19 -> -932.74436 | I19: =+E19/D19 -> 13.669519 | K19: Preguntas
A20: 16 | B20: =+E19 -> 245337.58 | C20: =+B20*Retiros!$M$8 -> 16950.596 | D20: =+D19*(1+Retiros!$B$12) -> 18486.218 | E20: =+B20+C20-D20 -> 243801.95 | G20: =+E20/(1+Retiros!$B$12) -> 236700.93 | H20: =+C20-D20 -> -1535.6221 | I20: =+E20/D20 -> 13.188309 | K20: ¿Cuándo los retiros son mayores que los ingresos?
A21: 17 | B21: =+E20 -> 243801.95 | C21: =+B21*Retiros!$M$8 -> 16844.499 | D21: =+D20*(1+Retiros!$B$12) -> 19040.805 | E21: =+B21+C21-D21 -> 241605.65 | G21: =+E21/(1+Retiros!$B$12) -> 234568.59 | H21: =+C21-D21 -> -2196.3061 | I21: =+E21/D21 -> 12.688836 | K21: ¿Por qué?
A22: 18 | B22: =+E21 -> 241605.65 | C22: =+B22*Retiros!$M$8 -> 16692.754 | D22: =+D21*(1+Retiros!$B$12) -> 19612.029 | E22: =+B22+C22-D22 -> 238686.37 | G22: =+E22/(1+Retiros!$B$12) -> 231734.34 | H22: =+C22-D22 -> -2919.2751 | I22: =+E22/D22 -> 12.170407 | K22: ¿Cuándo se agota el fondo?
A23: 19 | B23: =+E22 -> 238686.37 | C23: =+B23*Retiros!$M$8 -> 16491.058 | D23: =+D22*(1+Retiros!$B$12) -> 20200.39 | E23: =+B23+C23-D23 -> 234977.04 | G23: =+E23/(1+Retiros!$B$12) -> 228133.05 | H23: =+C23-D23 -> -3709.3313 | I23: =+E23/D23 -> 11.632302 | K23: ¿Por qué?
A24: 20 | B24: =+E23 -> 234977.04 | C24: =+B24*Retiros!$M$8 -> 16234.777 | D24: =+D23*(1+Retiros!$B$12) -> 20806.401 | E24: =+B24+C24-D24 -> 230405.42 | G24: =+E24/(1+Retiros!$B$12) -> 223694.58 | H24: =+C24-D24 -> -4571.6241 | I24: =+E24/D24 -> 11.073775 | K24: ¿Cómo cambia con inflación?
A25: 21 | B25: =+E24 -> 230405.42 | C25: =+B25*Retiros!$M$8 -> 15918.92 | D25: =+D24*(1+Retiros!$B$12) -> 21430.593 | E25: =+B25+C25-D25 -> 224893.74 | G25: =+E25/(1+Retiros!$B$12) -> 218343.44 | H25: =+C25-D25 -> -5511.6738 | I25: =+E25/D25 -> 10.494051
A26: 22 | B26: =+E25 -> 224893.74 | C26: =+B26*Retiros!$M$8 -> 15538.113 | D26: =+D25*(1+Retiros!$B$12) -> 22073.511 | E26: =+B26+C26-D26 -> 218358.35 | G26: =+E26/(1+Retiros!$B$12) -> 211998.39 | H26: =+C26-D26 -> -6535.3981 | I26: =+E26/D26 -> 9.8923249
A27: 23 | B27: =+E26 -> 218358.35 | C27: =+B27*Retiros!$M$8 -> 15086.577 | D27: =+D26*(1+Retiros!$B$12) -> 22735.717 | E27: =+B27+C27-D27 -> 210709.2 | G27: =+E27/(1+Retiros!$B$12) -> 204572.04 | H27: =+C27-D27 -> -7649.14 | I27: =+E27/D27 -> 9.2677618
A28: 24 | B28: =+E27 -> 210709.2 | C28: =+B28*Retiros!$M$8 -> 14558.091 | D28: =+D27*(1+Retiros!$B$12) -> 23417.788 | E28: =+B28+C28-D28 -> 201849.51 | G28: =+E28/(1+Retiros!$B$12) -> 195970.4 | H28: =+C28-D28 -> -8859.6976 | I28: =+E28/D28 -> 8.619495
A29: 25 | B29: =+E28 -> 201849.51 | C29: =+B29*Retiros!$M$8 -> 13945.966 | D29: =+D28*(1+Retiros!$B$12) -> 24120.322 | E29: =+B29+C29-D29 -> 191675.15 | G29: =+E29/(1+Retiros!$B$12) -> 186092.38 | H29: =+C29-D29 -> -10174.356 | I29: =+E29/D29 -> 7.946625
A30: 26 | B30: =+E29 -> 191675.15 | C30: =+B30*Retiros!$M$8 -> 13243.01 | D30: =+D29*(1+Retiros!$B$12) -> 24843.931 | E30: =+B30+C30-D30 -> 180074.23 | G30: =+E30/(1+Retiros!$B$12) -> 174829.35 | H30: =+C30-D30 -> -11600.921 | I30: =+E30/D30 -> 7.248218
A31: 27 | B31: =+E30 -> 180074.23 | C31: =+B31*Retiros!$M$8 -> 12441.492 | D31: =+D30*(1+Retiros!$B$12) -> 25589.249 | E31: =+B31+C31-D31 -> 166926.47 | G31: =+E31/(1+Retiros!$B$12) -> 162064.54 | H31: =+C31-D31 -> -13147.757 | I31: =+E31/D31 -> 6.5233048
A32: 28 | B32: =+E31 -> 166926.47 | C32: =+B32*Retiros!$M$8 -> 11533.102 | D32: =+D31*(1+Retiros!$B$12) -> 26356.927 | E32: =+B32+C32-D32 -> 152102.65 | G32: =+E32/(1+Retiros!$B$12) -> 147672.47 | H32: =+C32-D32 -> -14823.825 | I32: =+E32/D32 -> 5.7708795
A33: 29 | B33: =+E32 -> 152102.65 | C33: =+B33*Retiros!$M$8 -> 10508.91 | D33: =+D32*(1+Retiros!$B$12) -> 27147.635 | E33: =+B33+C33-D33 -> 135463.92 | G33: =+E33/(1+Retiros!$B$12) -> 131518.37 | H33: =+C33-D33 -> -16638.724 | I33: =+E33/D33 -> 4.9898979
A34: 30 | B34: =+E33 -> 135463.92 | C34: =+B34*Retiros!$M$8 -> 9359.3257 | D34: =+D33*(1+Retiros!$B$12) -> 27962.064 | E34: =+B34+C34-D34 -> 116861.19 | G34: =+E34/(1+Retiros!$B$12) -> 113457.46 | H34: =+C34-D34 -> -18602.738 | I34: =+E34/D34 -> 4.1792762
A35: 31 | B35: =+E34 -> 116861.19 | C35: =+B35*Retiros!$M$8 -> 8074.0456 | D35: =+D34*(1+Retiros!$B$12) -> 28800.926 | E35: =+B35+C35-D35 -> 96134.306 | G35: =+E35/(1+Retiros!$B$12) -> 93334.278 | H35: =+C35-D35 -> -20726.88 | I35: =+E35/D35 -> 3.3378895
A36: 32 | B36: =+E35 -> 96134.306 | C36: =+B36*Retiros!$M$8 -> 6642.0066 | D36: =+D35*(1+Retiros!$B$12) -> 29664.953 | E36: =+B36+C36-D36 -> 73111.36 | G36: =+E36/(1+Retiros!$B$12) -> 70981.902 | H36: =+C36-D36 -> -23022.947 | I36: =+E36/D36 -> 2.4645702
... A44: 40 | B44: =+E43 -> -169673.17 | C44: =+B44*Retiros!$M$8 -> -11722.874 | D44: =+D43*(1+Retiros!$B$12) -> 37578.675 | E44: =+B44+C44-D44 -> -218974.72 | G44: =+E44/(1+Retiros!$B$12) -> -212596.81 | H44: =+C44-D44 -> -49301.549 | I44: =+E44/D44 -> -5.8271005
